setup.py
django_raven_metlog.egg-info/PKG-INFO
django_raven_metlog.egg-info/SOURCES.txt
django_raven_metlog.egg-info/dependency_links.txt
django_raven_metlog.egg-info/not-zip-safe
django_raven_metlog.egg-info/requires.txt
django_raven_metlog.egg-info/top_level.txt
djangoraven/__init__.py
djangoraven/metlog.py
tests/contrib/__init__.py
tests/contrib/django/__init__.py
tests/contrib/django/middleware.py
tests/contrib/django/models.py
tests/contrib/django/tests.py
tests/contrib/django/urls.py
tests/contrib/django/views.py